mapreduce/__init__.py
mapreduce/mapreduce.py
mapreduce_py-0.5.1.dist-info/LICENSE
mapreduce_py-0.5.1.dist-info/METADATA
mapreduce_py-0.5.1.dist-info/WHEEL
mapreduce_py-0.5.1.dist-info/top_level.txt
mapreduce_py-0.5.1.dist-info/RECORD
