Metadata-Version: 1.1
Name: mapreduce-py
Version: 0.5.1
Summary: "A simple multi-processing based MapReduce framework"
Home-page: https://github.com/royqh1979/pymapreduce
Author: Roy Qu
Author-email: royqh1979@gmail.com
License: MIT
Keywords: MapReduce,functional
Platform: UNKNOWN
Classifier: Development Status :: 4 - Beta
Classifier: License :: OSI Approved :: BSD License
Classifier: Topic :: Software Development :: Libraries
Classifier: Topic :: Utilities
Classifier: Programming Language :: Python :: 3
Classifier: Programming Language :: Python :: 3.5
Classifier: Programming Language :: Python :: 3.6
Classifier: Programming Language :: Python :: 3.7
